{
    "basics": {
        "name": "Deepika Gunda",
        "label": "Architect",
        "image": "https://www.thispersondoesnotexist.com/image",
        "summary": "I am a software engineer who has experience in developing and maintain systems used by million of users. I consider myself as a detail and process oriented person. Learning and sharing have become my passion. I embrace for a new challenge and learning new things.",
        "email": "deepika-gunda@gmail.com",
        "location": {
            "city": "Tokyo",
            "countryCode": "US"
        }
    },
    "references": [
        {
            "reference": "The product owner at fuga",
            "name": "Dylan Wilson"
        },
        {
            "reference": "Deepika is a hard working, reliable personable expert in it his field. Him even though given a great ability to problem. Not always looking to design technical capabilities and he makes him a great asset to any team that he.",
            "name": "Andrew Avdeev"
        }
    ],
    "work": [
        {
            "highlights": [
                "Login server deployment",
                "Learned how to work."
            ],
            "summary": "I worked on preparing the system for heavy load generated by thousands of devices. I was involved in designing and optimizing managing the infrastructure as well as the actual development stack.",
            "website": "http://tigar-a-d-rubber-company-retail-wholesale.com",
            "company": "Tigar A D Rubber Company, Retail & Wholesale",
            "position": "Senior Software Engineer / Team Lead",
            "startDate": "2018-01-08",
            "endDate": "2020-09-08"
        },
        {
            "highlights": [
                "Started existing products with over 40 000 websites selling saving over the year 10 items",
                "Moved the code from svn to git"
            ],
            "summary": "Working on the core data and implemented features as the presence of the product",
            "website": "http://netboundary.com",
            "company": "Netboundary",
            "position": "Senior Software Engineer / Product Manager (backend Services)",
            "startDate": "2015-02-07",
            "endDate": "2018-01-01"
        },
        {
            "highlights": [
                "Planned all the designed and maintained the for the use of the website",
                "Maintained the performance of the integrated eCommerce platform."
            ],
            "summary": "Is a leading private school,.",
            "website": "http://tutorific.com",
            "company": "Tutorific",
            "position": "Senior Software Engineer Ii",
            "startDate": "2014-09-01",
            "endDate": "2015-01-01"
        }
    ],
    "interests": [
        {
            "name": "A Good Book"
        },
        {
            "name": "Management"
        },
        {
            "name": "Internet Of Thing"
        }
    ]
}